amzn_nova_customization_sdk/__init__.py
amzn_nova_customization_sdk/__version__.py
amzn_nova_customization_sdk/py.typed
amzn_nova_customization_sdk/dataset/__init__.py
amzn_nova_customization_sdk/dataset/dataset_format_schema.py
amzn_nova_customization_sdk/dataset/dataset_loader.py
amzn_nova_customization_sdk/dataset/dataset_transformers.py
amzn_nova_customization_sdk/dataset/transform_format_schema.py
amzn_nova_customization_sdk/dataset/dataset_validator/__init__.py
amzn_nova_customization_sdk/dataset/dataset_validator/cpt_dataset_validator.py
amzn_nova_customization_sdk/dataset/dataset_validator/dataset_validator.py
amzn_nova_customization_sdk/dataset/dataset_validator/eval_dataset_validator.py
amzn_nova_customization_sdk/dataset/dataset_validator/rft_dataset_validator.py
amzn_nova_customization_sdk/dataset/dataset_validator/sft_dataset_validator.py
amzn_nova_customization_sdk/manager/__init__.py
amzn_nova_customization_sdk/manager/runtime_manager.py
amzn_nova_customization_sdk/model/__init__.py
amzn_nova_customization_sdk/model/model_config.py
amzn_nova_customization_sdk/model/model_enums.py
amzn_nova_customization_sdk/model/nova_model_customizer.py
amzn_nova_customization_sdk/model/nova_model_customizer_util.py
amzn_nova_customization_sdk/model/result/__init__.py
amzn_nova_customization_sdk/model/result/eval_result.py
amzn_nova_customization_sdk/model/result/inference_result.py
amzn_nova_customization_sdk/model/result/job_result.py
amzn_nova_customization_sdk/model/result/training_result.py
amzn_nova_customization_sdk/monitor/__init__.py
amzn_nova_customization_sdk/monitor/log_monitor.py
amzn_nova_customization_sdk/monitor/mlflow_monitor.py
amzn_nova_customization_sdk/recipe/__init__.py
amzn_nova_customization_sdk/recipe/recipe_builder.py
amzn_nova_customization_sdk/recipe/recipe_config.py
amzn_nova_customization_sdk/util/__init__.py
amzn_nova_customization_sdk/util/bedrock.py
amzn_nova_customization_sdk/util/checkpoint_util.py
amzn_nova_customization_sdk-1.0.83.dist-info/licenses/LICENSE
amzn_nova_customization_sdk-1.0.83.dist-info/licenses/NOTICE
amzn_nova_customization_sdk-1.0.83.dist-info/METADATA
amzn_nova_customization_sdk-1.0.83.dist-info/WHEEL
amzn_nova_customization_sdk-1.0.83.dist-info/top_level.txt
amzn_nova_customization_sdk-1.0.83.dist-info/RECORD
