Metadata-Version: 2.4
Name: amzn-nova-customization-sdk
Version: 1.0.83
Summary: A Python SDK for customizing Amazon Nova models.
Author-email: Amazon <nova-customizersdk@amazon.com>
License-Expression: Apache-2.0
Requires-Python: >=3.12
License-File: LICENSE
License-File: NOTICE
Requires-Dist: annotated-doc==0.0.4
Requires-Dist: annotated-types==0.7.0
Requires-Dist: antlr4-python3-runtime==4.9.3
Requires-Dist: anyio==4.12.0
Requires-Dist: attrs==25.4.0
Requires-Dist: boto3==1.42.3
Requires-Dist: botocore==1.42.3
Requires-Dist: certifi==2025.11.12
Requires-Dist: charset-normalizer==3.4.4
Requires-Dist: click==8.3.1
Requires-Dist: cloudpickle==3.1.2
Requires-Dist: dill==0.4.0
Requires-Dist: docker==7.1.0
Requires-Dist: fastapi==0.123.9
Requires-Dist: google-pasta==0.2.0
Requires-Dist: graphene==3.4.3
Requires-Dist: graphql-core==3.2.7
Requires-Dist: graphql-relay==3.2.0
Requires-Dist: h11==0.16.0
Requires-Dist: idna==3.11
Requires-Dist: importlib-metadata==6.11.0
Requires-Dist: iniconfig==2.3.0
Requires-Dist: jmespath==1.0.1
Requires-Dist: jsonschema==4.25.1
Requires-Dist: jsonschema-specifications==2025.9.1
Requires-Dist: librt==0.6.3
Requires-Dist: markdown-it-py==4.0.0
Requires-Dist: mdurl==0.1.2
Requires-Dist: mock==4.0.3
Requires-Dist: multiprocess==0.70.18
Requires-Dist: mypy==1.19.0
Requires-Dist: mypy-extensions==1.1.0
Requires-Dist: numpy==1.26.4
Requires-Dist: omegaconf==2.3.0
Requires-Dist: packaging==24.2
Requires-Dist: pandas==2.3.3
Requires-Dist: pathos==0.3.4
Requires-Dist: pathspec==0.12.1
Requires-Dist: platformdirs==4.5.1
Requires-Dist: pluggy==1.6.0
Requires-Dist: pox==0.3.6
Requires-Dist: ppft==1.7.7
Requires-Dist: protobuf==6.31.1
Requires-Dist: psutil==7.1.3
Requires-Dist: pydantic==2.12.5
Requires-Dist: pydantic-core==2.41.5
Requires-Dist: pygments==2.19.2
Requires-Dist: pytest==9.0.1
Requires-Dist: python-dateutil==2.9.0.post0
Requires-Dist: pytz==2025.2
Requires-Dist: pyyaml==6.0.3
Requires-Dist: referencing==0.37.0
Requires-Dist: requests==2.32.5
Requires-Dist: rich==14.2.0
Requires-Dist: rpds-py==0.30.0
Requires-Dist: ruff==0.14.8
Requires-Dist: s3transfer==0.16.0
Requires-Dist: sagemaker==2.254.1
Requires-Dist: sagemaker-core==1.0.71
Requires-Dist: schema==0.7.8
Requires-Dist: six==1.17.0
Requires-Dist: smdebug-rulesconfig==1.0.1
Requires-Dist: starlette==0.50.0
Requires-Dist: tblib==3.2.2
Requires-Dist: tqdm==4.67.1
Requires-Dist: typing-extensions==4.15.0
Requires-Dist: typing-inspection==0.4.2
Requires-Dist: tzdata==2025.2
Requires-Dist: urllib3==2.6.0
Requires-Dist: uvicorn==0.38.0
Requires-Dist: zipp==3.23.0
Provides-Extra: dev
Requires-Dist: build; extra == "dev"
Requires-Dist: setuptools; extra == "dev"
Requires-Dist: twine; extra == "dev"
Requires-Dist: wheel; extra == "dev"
Dynamic: license-file
